{
  "vacinas": [
    {
      "nome": "COVID-19 - Pfizer",
      "dose": 1,
      "data_vacinacao": "12/08/2021",
      "dose_complementar": true,
      "data_vacinacao_dose_complementar": "06/10/2021",
      "inicio_previsao": "05/10/2021",
      "fim_previsao": "08/11/2021",
      "fabricante": "PFIZER MANUFACTURING BELGIUM NV - BELGICA",
      "lote": "31065BD",
      "profissional_aplicador": "Rita Catarina Tonico da Cunha",
      "estabelecimento_saude": "HOSPITAL MATERNIDADE DO DIVINO AMOR"
    },
    {
      "nome": "COVID-19 - Pfizer",
      "dose": 2,
      "data_vacinacao": "23/11/2021",
      "dose_complementar": false,
      "data_vacinacao_dose_complementar": "06/10/2021",
      "inicio_previsao": "05/10/2021",
      "fim_previsao": "08/11/2021",
      "fabricante": "PFIZER MANUFACTURING BELGIUM NV - BELGICA",
      "lote": "31065BD",
      "profissional_aplicador": "Rita Catarina Tonico da Cunha",
      "estabelecimento_saude": "HOSPITAL MATERNIDADE DO DIVINO AMOR"
    },
    {
      "nome": "VACINA X",
      "dose": 1,
      "data_vacinacao": "12/08/2021",
      "dose_complementar": false,
      "data_vacinacao_dose_complementar": null,
      "inicio_previsao": null,
      "fim_previsao": null,
      "fabricante": "fabricante X",
      "lote": "23HK29H",
      "profissional_aplicador": "joao",
      "estabelecimento_saude": "hospital X"
    },
    {
      "nome": "VACINA Y",
      "data_vacinacao": "12/08/2021",
      "dose": 1,
      "dose_complementar": true,
      "data_vacinacao_dose_complementar": null,
      "inicio_previsao": "05/10/2021",
      "fim_previsao": "08/11/2021",
      "fabricante": "fabricante y",
      "lote": "1OHK26H",
      "profissional_aplicador": "maria",
      "estabelecimento_saude": "hospital Y"
    }
  ]
}
